setup.py
strap/__init__.py
strap/client.py
strap/server.py
strap.egg-info/PKG-INFO
strap.egg-info/SOURCES.txt
strap.egg-info/dependency_links.txt
strap.egg-info/requires.txt
strap.egg-info/top_level.txt
strap/rdflib_impl/__init__.py
strap/rdflib_impl/client.py
strap/rdflib_impl/handler.py