Metadata-Version: 1.0
Name: strap
Version: 0.4
Summary: Simple sTreamed Rdf Access Protocol
Home-page: http://champin.net/dev/strap/
Author: Pierre-Antoine Champin
Author-email: strap@champin.net
License: GNU LGPL v2.1
Keywords: rdf semantic-web component rdflib
Platform: All
